fiddler_evals/VERSION
fiddler_evals/__init__.py
fiddler_evals/configs.py
fiddler_evals/conftest.py
fiddler_evals/connection.py
fiddler_evals/constants.py
fiddler_evals/decorators.py
fiddler_evals/exceptions.py
fiddler_evals/version.py
fiddler_evals/entities/__init__.py
fiddler_evals/entities/application.py
fiddler_evals/entities/base.py
fiddler_evals/entities/dataset.py
fiddler_evals/entities/experiment.py
fiddler_evals/entities/project.py
fiddler_evals/entities/tests/__init__.py
fiddler_evals/entities/tests/test_application.py
fiddler_evals/entities/tests/test_dataset.py
fiddler_evals/entities/tests/test_dataset_items.py
fiddler_evals/entities/tests/test_experiment.py
fiddler_evals/entities/tests/test_experiment_items.py
fiddler_evals/entities/tests/test_experiment_results.py
fiddler_evals/entities/tests/test_project.py
fiddler_evals/evaluators/__init__.py
fiddler_evals/evaluators/answer_relevance.py
fiddler_evals/evaluators/base.py
fiddler_evals/evaluators/coherence.py
fiddler_evals/evaluators/conciseness.py
fiddler_evals/evaluators/eval_fn.py
fiddler_evals/evaluators/ftl_prompt_safety.py
fiddler_evals/evaluators/ftl_response_faithfulness.py
fiddler_evals/evaluators/regex.py
fiddler_evals/evaluators/sentiment.py
fiddler_evals/evaluators/topic.py
fiddler_evals/evaluators/tests/__init__.py
fiddler_evals/evaluators/tests/test_answer_relevance.py
fiddler_evals/evaluators/tests/test_coherence.py
fiddler_evals/evaluators/tests/test_conciseness.py
fiddler_evals/evaluators/tests/test_eval_fn.py
fiddler_evals/evaluators/tests/test_ftl_prompt_safety.py
fiddler_evals/evaluators/tests/test_ftl_response_faithfulness.py
fiddler_evals/evaluators/tests/test_regex.py
fiddler_evals/evaluators/tests/test_sentiment.py
fiddler_evals/evaluators/tests/test_topic_classification.py
fiddler_evals/libs/__init__.py
fiddler_evals/libs/http_client.py
fiddler_evals/libs/json_encoder.py
fiddler_evals/libs/semver.py
fiddler_evals/libs/tests/__init__.py
fiddler_evals-0.2.0.dist-info/METADATA
fiddler_evals-0.2.0.dist-info/WHEEL
fiddler_evals-0.2.0.dist-info/top_level.txt
fiddler_evals-0.2.0.dist-info/RECORD
