Metadata-Version: 2.4
Name: fiddler-evals
Version: 0.2.0
Summary: Python SDK for evaluating LLM Applications
Author-email: Fiddler AI <support@fiddler.ai>
Maintainer-email: Fiddler AI <support@fiddler.ai>
Project-URL: Homepage, https://fiddler.ai
Project-URL: Documentation, https://docs.fiddler.ai/
Classifier: Programming Language :: Python :: 3
Classifier: Operating System :: OS Independent
Requires-Python: >=3.10
Requires-Dist: pip>=21.0
Requires-Dist: requests<3
Requires-Dist: pydantic>=2.0.0
Requires-Dist: tqdm
Requires-Dist: typing-extensions<5,>=4.6.0
Requires-Dist: python-decouple
Provides-Extra: pandas
Requires-Dist: pandas>=1.2.5; extra == "pandas"
